pygame/SDL2.dll
pygame/SDL2_image.dll
pygame/SDL2_mixer.dll
pygame/SDL2_ttf.dll
pygame/__init__.py
pygame/__init__.pyi
pygame/_camera.cp310-win_amd64.pyd
pygame/_camera_opencv.py
pygame/_camera_vidcapture.py
pygame/_common.pyi
pygame/_freetype.cp310-win_amd64.pyd
pygame/_sprite.cp310-win_amd64.pyd
pygame/base.cp310-win_amd64.pyd
pygame/base.pyi
pygame/bufferproxy.cp310-win_amd64.pyd
pygame/bufferproxy.pyi
pygame/camera.py
pygame/camera.pyi
pygame/color.cp310-win_amd64.pyd
pygame/color.pyi
pygame/colordict.py
pygame/constants.cp310-win_amd64.pyd
pygame/constants.pyi
pygame/cursors.py
pygame/cursors.pyi
pygame/display.cp310-win_amd64.pyd
pygame/display.pyi
pygame/draw.cp310-win_amd64.pyd
pygame/draw.pyi
pygame/draw_py.py
pygame/event.cp310-win_amd64.pyd
pygame/event.pyi
pygame/fastevent.py
pygame/fastevent.pyi
pygame/font.cp310-win_amd64.pyd
pygame/font.pyi
pygame/freesansbold.ttf
pygame/freetype.dll
pygame/freetype.py
pygame/freetype.pyi
pygame/ftfont.py
pygame/gfxdraw.cp310-win_amd64.pyd
pygame/gfxdraw.pyi
pygame/image.cp310-win_amd64.pyd
pygame/image.pyi
pygame/imageext.cp310-win_amd64.pyd
pygame/joystick.cp310-win_amd64.pyd
pygame/joystick.pyi
pygame/key.cp310-win_amd64.pyd
pygame/key.pyi
pygame/libjpeg-9.dll
pygame/libmodplug-1.dll
pygame/libogg-0.dll
pygame/libopus-0.dll
pygame/libopusfile-0.dll
pygame/libpng16-16.dll
pygame/libtiff-5.dll
pygame/libwebp-7.dll
pygame/locals.py
pygame/locals.pyi
pygame/macosx.py
pygame/mask.cp310-win_amd64.pyd
pygame/mask.pyi
pygame/math.cp310-win_amd64.pyd
pygame/math.pyi
pygame/midi.py
pygame/midi.pyi
pygame/mixer.cp310-win_amd64.pyd
pygame/mixer.pyi
pygame/mixer_music.cp310-win_amd64.pyd
pygame/mixer_music.pyi
pygame/mouse.cp310-win_amd64.pyd
pygame/mouse.pyi
pygame/newbuffer.cp310-win_amd64.pyd
pygame/pixelarray.cp310-win_amd64.pyd
pygame/pixelarray.pyi
pygame/pixelcopy.cp310-win_amd64.pyd
pygame/pixelcopy.pyi
pygame/pkgdata.py
pygame/portmidi.dll
pygame/py.typed
pygame/pygame.ico
pygame/pygame_icon.bmp
pygame-2.6.1.dist-info/METADATA
pygame-2.6.1.dist-info/WHEEL
pygame-2.6.1.dist-info/entry_points.txt
pygame-2.6.1.dist-info/top_level.txt
pygame-2.6.1.dist-info/RECORD
